githubflow_release/__init__.py
githubflow_release/release.py
githubflow_release-0.0.2.dist-info/COPYING.txt
githubflow_release-0.0.2.dist-info/METADATA
githubflow_release-0.0.2.dist-info/WHEEL
githubflow_release-0.0.2.dist-info/entry_points.txt
githubflow_release-0.0.2.dist-info/top_level.txt
githubflow_release-0.0.2.dist-info/RECORD
